sage_sample/__init__.py
sage_sample/ultimate_question.py
sage_sample-0.3.0.dist-info/DESCRIPTION.rst
sage_sample-0.3.0.dist-info/METADATA
sage_sample-0.3.0.dist-info/RECORD
sage_sample-0.3.0.dist-info/WHEEL
sage_sample-0.3.0.dist-info/metadata.json
sage_sample-0.3.0.dist-info/top_level.txt
