Metadata-Version: 2.0
Name: sage-sample
Version: 0.3.0
Summary: An example of a basic sage package
Home-page: https://github.com/sagemath/sage_sample
Author: Matthias Koeppe, Sébastien Labbé, Viviane Pons, Nicolas M. Thiéry, ... with inspiration from many
Author-email: viviane.pons@lri.fr
License: GPLv2+
Keywords: SageMath packaging
Platform: UNKNOWN
Classifier: Development Status :: 4 - Beta
Classifier: Intended Audience :: Science/Research
Classifier: Topic :: Software Development :: Build Tools
Classifier: Topic :: Scientific/Engineering :: Mathematics
Classifier: License :: OSI Approved :: GNU General Public License v2 or later (GPLv2+)
Classifier: Programming Language :: Python :: 2.7
Requires-Dist: sage-package
Requires-Dist: sphinx
